pytwwa5
