Metadata-Version: 1.0
Name: pytwwa5
Version: 0.9
Summary: Our first Python distribution package
Home-page: UNKNOWN
Author: Unknown
Author-email: unknown@gmail.com
License: UNKNOWN
Platform: UNKNOWN
